robin/install/__init__.py
robin/install/bootstrap_gen.py
robin/install/envs.py
robin/install/utils.py
robin/install/version.py
robin_install-1.0.0.dist-info/METADATA
robin_install-1.0.0.dist-info/WHEEL
robin_install-1.0.0.dist-info/entry_points.txt
robin_install-1.0.0.dist-info/licenses/LICENSE
robin_install-1.0.0.dist-info/RECORD
