Metadata-Version: 2.4
Name: robin-install
Version: 1.0.0
Summary: Robin Install.
Project-URL: Homepage, https://www.gmicloud.ai/
Project-URL: Repository, https://www.gmicloud.ai/
Author-email: robin <yanhong.l@gmicloud.ai>
License-Expression: Apache-2.0
License-File: LICENSE
Classifier: Development Status :: 4 - Beta
Classifier: Intended Audience :: Developers
Classifier: License :: OSI Approved :: Apache Software License
Classifier: Programming Language :: Python
Classifier: Programming Language :: Python :: 3
Classifier: Programming Language :: Python :: 3.9
Classifier: Programming Language :: Python :: 3.10
Classifier: Programming Language :: Python :: 3.11
Classifier: Programming Language :: Python :: 3.12
Classifier: Programming Language :: Python :: 3.13
Requires-Python: >=3.9
Requires-Dist: opentelemetry-api~=1.4
Requires-Dist: packaging>=18.0
Requires-Dist: requests
Requires-Dist: wrapt<2.0.0,>=1.0.0
